oubli/__init__.py
oubli/cli.py
oubli/config.py
oubli/core_memory.py
oubli/embeddings.py
oubli/mcp_server.py
oubli/storage.py
oubli/viz.py
oubli/data/CLAUDE.md
oubli/data/commands/clear-memories.md
oubli/data/commands/synthesize.md
oubli/data/commands/visualize-memory.md
oubli-0.4.8.dist-info/METADATA
oubli-0.4.8.dist-info/WHEEL
oubli-0.4.8.dist-info/entry_points.txt
oubli-0.4.8.dist-info/licenses/LICENSE
oubli-0.4.8.dist-info/RECORD
