Metadata-Version: 2.4
Name: oubli
Version: 0.4.8
Summary: Fractal memory system for Claude Code
Project-URL: Homepage, https://github.com/dremok/oubli
Project-URL: Repository, https://github.com/dremok/oubli
Author: Max Leander
License: MIT
License-File: LICENSE
Keywords: ai,claude,claude-code,llm,memory
Classifier: Development Status :: 3 - Alpha
Classifier: Intended Audience :: Developers
Classifier: License :: OSI Approved :: MIT License
Classifier: Programming Language :: Python :: 3
Classifier: Programming Language :: Python :: 3.10
Classifier: Programming Language :: Python :: 3.11
Classifier: Programming Language :: Python :: 3.12
Requires-Python: >=3.10
Requires-Dist: click>=8.0.0
Requires-Dist: lancedb>=0.4.0
Requires-Dist: mcp>=1.0.0
Requires-Dist: pyarrow>=14.0.0
Requires-Dist: sentence-transformers>=2.2.0
